CHANGES.txt
COPYING.txt
MANIFEST.in
README.rst
setup.py
tappio/__init__.py
tappio/lexer.py
tappio/models.py
tappio/parser.py
tappio/writer.py
tappio/scripts/__init__.py
tappio/scripts/extract.py
tappio/scripts/graph.py
tappio/scripts/indent.py
tappio/scripts/merge.py
tappio/scripts/missing_accounts.py
tappio/scripts/move_entries.py
tappio/scripts/print_accounts.py
tappio/scripts/print_earnings.py
tappio/scripts/renumber.py
voitto/__init__.py
voitto.egg-info/PKG-INFO
voitto.egg-info/SOURCES.txt
voitto.egg-info/dependency_links.txt
voitto.egg-info/entry_points.txt
voitto.egg-info/top_level.txt
voitto.egg-info/zip-safe
voitto/helpers/__init__.py
voitto/helpers/tracer.py