Metadata-Version: 1.0
Name: voitto
Version: 0.0.1
Summary: A simple yet efficient double ledger
Home-page: http://github.com/japsu/voitto
Author: Santtu Pajukanta
Author-email: santtu@pajukanta.fi
License: GPLv3+
Platform: UNKNOWN
Classifier: Development Status :: 3 - Alpha
Classifier: Environment :: Console
Classifier: Intended Audience :: End Users/Desktop
Classifier: Intended Audience :: Financial and Insurance Industry
Classifier: License :: OSI Approved :: GNU General Public License v3 or later (GPLv3+)
Classifier: Natural Language :: English
Classifier: Natural Language :: Finnish
Classifier: Operating System :: Microsoft :: Windows
Classifier: Operating System :: POSIX :: Linux
Classifier: Programming Language :: Python :: 2.7
Classifier: Topic :: Office/Business :: Financial :: Accounting
